host.py
space_for_everyone-0.1.2.dist-info/METADATA
space_for_everyone-0.1.2.dist-info/WHEEL
space_for_everyone-0.1.2.dist-info/entry_points.txt
space_for_everyone-0.1.2.dist-info/top_level.txt
space_for_everyone-0.1.2.dist-info/RECORD
