Metadata-Version: 2.4
Name: space-for-everyone
Version: 0.1.2
Summary: Host anywhere amd anytime - Instant Preview Link
Author-email: Sid & Kan <sofiyasenthilkumar@gmail.com>
License: MIT
Requires-Python: >=3.8
Requires-Dist: requests>=2.28
